biftest/__init__.py
biftest/dashboard_manager.py
biftest/data_manager.py
biftest/hel.py
biftest/request.py
biftest/system_manager.py
biftest-0.1.0.dist-info/METADATA
biftest-0.1.0.dist-info/WHEEL
biftest-0.1.0.dist-info/top_level.txt
biftest-0.1.0.dist-info/RECORD
