Metadata-Version: 2.1
Name: biftest
Version: 0.1.0
Summary: UNKNOWN
Home-page: UNKNOWN
License: UNKNOWN
Platform: UNKNOWN
Requires-Dist: pandas (>=1.0)
Requires-Dist: matplotlib (>=3.1)
Requires-Dist: requests
Requires-Dist: seaborn (>=0.10)
